.gitignore
.gitlab-ci.yml
.pylintrc
CHANGELOG.md
CODE_OF_CONDUCT.md
CONTRIBUTING.md
CONTRIBUTORS.md
LICENSE
MANIFEST.in
Makefile
README.md
codecov.yml
pyproject.toml
requirements.txt
setup.cfg
setup.py
variables
./variables
.github/workflows/pythonpackage.yml
docs/Makefile
docs/make.bat
docs/source/conf.py
docs/source/index.rst
files/profile
typings/setuptools/__init__.pyi
typings/setuptools/_deprecation_warning.pyi
typings/setuptools/_imp.pyi
typings/setuptools/archive_util.pyi
typings/setuptools/build_meta.pyi
typings/setuptools/config.pyi
typings/setuptools/dep_util.pyi
typings/setuptools/depends.pyi
typings/setuptools/dist.pyi
typings/setuptools/errors.pyi
typings/setuptools/extension.pyi
typings/setuptools/glob.pyi
typings/setuptools/installer.pyi
typings/setuptools/launch.pyi
typings/setuptools/lib2to3_ex.pyi
typings/setuptools/monkey.pyi
typings/setuptools/msvc.pyi
typings/setuptools/namespaces.pyi
typings/setuptools/package_index.pyi
typings/setuptools/py34compat.pyi
typings/setuptools/sandbox.pyi
typings/setuptools/ssl_support.pyi
typings/setuptools/unicode_utils.pyi
typings/setuptools/version.pyi
typings/setuptools/wheel.pyi
typings/setuptools/windows_support.pyi
typings/setuptools/_distutils/__init__.pyi
typings/setuptools/_vendor/__init__.pyi
typings/setuptools/command/__init__.pyi
typings/setuptools/command/bdist_egg.pyi
typings/setuptools/command/easy_install.pyi
typings/setuptools/command/egg_info.pyi
typings/setuptools/command/install_scripts.pyi
typings/setuptools/command/py36compat.pyi
typings/setuptools/command/sdist.pyi
typings/setuptools/command/setopt.pyi
typings/setuptools/extern/__init__.pyi
venvctl/__init__.py
venvctl/__main__.py
venvctl.egg-info/PKG-INFO
venvctl.egg-info/SOURCES.txt
venvctl.egg-info/dependency_links.txt
venvctl.egg-info/entry_points.txt
venvctl.egg-info/not-zip-safe
venvctl.egg-info/requires.txt
venvctl.egg-info/top_level.txt
venvctl/cli/__init__.py
venvctl/cli/main.py
venvctl/cli/options.py
venvctl/main/__init__.py
venvctl/main/release.py
venvctl/main/venv.py
venvctl/main/venvctl.py
venvctl/tests/__init__.py
venvctl/tests/test_configutils.py
venvctl/tests/test_unit.py
venvctl/tests/config/venvs.json
venvctl/utils/__init__.py
