Metadata-Version: 2.1
Name: venvctl
Version: 1.4.12
Summary: A package to create portable virtual environments programmatically.
Home-page: https://gitlab.com/hyperd/venvctl
Author: hyperd
Author-email: fc@hyperd.sh
License: GPL-3.0
Project-URL: Documentation, https://gitlab.com/hyperd/venvctl
Project-URL: Source, https://venvctl.readthedocs.io/en/latest/
Platform: UNKNOWN
Classifier: Development Status :: 5 - Production/Stable
Classifier: Operating System :: OS Independent
Classifier: Intended Audience :: Developers
Classifier: Intended Audience :: Information Technology
Classifier: Intended Audience :: System Administrators
Classifier: License :: OSI Approved :: GNU General Public License v3 (GPLv3)
Classifier: Programming Language :: Python :: 3
Classifier: Programming Language :: Python :: 3.6
Classifier: Programming Language :: Python :: 3.7
Classifier: Programming Language :: Python :: 3.8
Classifier: Programming Language :: Python :: 3.9
Classifier: Natural Language :: English
Classifier: Operating System :: POSIX
Classifier: Operating System :: MacOS :: MacOS X
Classifier: Topic :: Software Development :: Libraries
Classifier: Topic :: Utilities
Classifier: Environment :: Plugins
Requires-Python: >=3.6
License-File: LICENSE
